agent/models.py
agent/apps.py
agent/__init__.py
neo_agent-0.1.3.dist-info/RECORD
neo_agent-0.1.3.dist-info/DESCRIPTION.rst
neo_agent-0.1.3.dist-info/WHEEL
neo_agent-0.1.3.dist-info/metadata.json
neo_agent-0.1.3.dist-info/top_level.txt
neo_agent-0.1.3.dist-info/METADATA
