Metadata-Version: 2.0
Name: neo-agent
Version: 0.1.3
Summary: USSD session app for Django.
Home-page: https://github.com/deone/neo-agent
Author: Dayo Osikoya
Author-email: alwaysdeone@gmail.com
License: MIT
Keywords: ussd http session json response django
Platform: UNKNOWN
Classifier: Development Status :: 5 - Production/Stable
Classifier: Intended Audience :: Developers
Classifier: Topic :: Software Development :: Build Tools
Classifier: License :: OSI Approved :: MIT License
Classifier: Programming Language :: Python :: 2
Classifier: Programming Language :: Python :: 2.6
Classifier: Programming Language :: Python :: 2.7
Requires-Dist: Django (==1.11.5)
